odoo/addons/edi_exchange_template_oca/README.rst
odoo/addons/edi_exchange_template_oca/__init__.py
odoo/addons/edi_exchange_template_oca/__manifest__.py
odoo/addons/edi_exchange_template_oca/utils.py
odoo/addons/edi_exchange_template_oca/i18n/edi_exchange_template.pot
odoo/addons/edi_exchange_template_oca/i18n/edi_exchange_template_oca.pot
odoo/addons/edi_exchange_template_oca/i18n/it.po
odoo/addons/edi_exchange_template_oca/migrations/18.0.1.2.0/pre-migrate.py
odoo/addons/edi_exchange_template_oca/migrations/18.0.1.3.0/post-migrate.py
odoo/addons/edi_exchange_template_oca/models/__init__.py
odoo/addons/edi_exchange_template_oca/models/edi_backend.py
odoo/addons/edi_exchange_template_oca/models/edi_exchange_template_mixin.py
odoo/addons/edi_exchange_template_oca/models/edi_exchange_template_output.py
odoo/addons/edi_exchange_template_oca/models/edi_exchange_type.py
odoo/addons/edi_exchange_template_oca/models/edi_oca_template_handler.py
odoo/addons/edi_exchange_template_oca/readme/CONTRIBUTORS.md
odoo/addons/edi_exchange_template_oca/readme/DESCRIPTION.md
odoo/addons/edi_exchange_template_oca/security/ir_model_access.xml
odoo/addons/edi_exchange_template_oca/static/description/icon.png
odoo/addons/edi_exchange_template_oca/static/description/index.html
odoo/addons/edi_exchange_template_oca/tests/__init__.py
odoo/addons/edi_exchange_template_oca/tests/test_backend_and_type.py
odoo/addons/edi_exchange_template_oca/tests/test_edi_backend_output.py
odoo/addons/edi_exchange_template_oca/tests/test_nswrapper.py
odoo/addons/edi_exchange_template_oca/views/edi_exchange_template_output_views.xml
odoo/addons/edi_exchange_template_oca/views/edi_exchange_type_views.xml
odoo_addon_edi_exchange_template_oca-18.0.1.3.2.dist-info/METADATA
odoo_addon_edi_exchange_template_oca-18.0.1.3.2.dist-info/WHEEL
odoo_addon_edi_exchange_template_oca-18.0.1.3.2.dist-info/top_level.txt
odoo_addon_edi_exchange_template_oca-18.0.1.3.2.dist-info/RECORD
