Metadata-Version: 2.1
Name: odoo-addon-edi_exchange_template_oca
Version: 18.0.1.3.2
Requires-Python: >=3.10
Requires-Dist: odoo-addon-edi_core_oca==18.0.*
Requires-Dist: odoo==18.0.*
Summary: Allows definition of exchanges via templates.
Home-page: https://github.com/OCA/edi-framework
License: LGPL-3
Author: ACSONE,Camptocamp,Odoo Community Association (OCA)
Author-email: support@odoo-community.org
Classifier: Programming Language :: Python
Classifier: Framework :: Odoo
Classifier: Framework :: Odoo :: 18.0
Classifier: License :: OSI Approved :: GNU Lesser General Public License v3 (LGPLv3)
Classifier: Development Status :: 4 - Beta
